README.md
setup.py
frasco_upload/__init__.py
frasco_upload/backends.py
frasco_upload/form.py
frasco_upload/utils.py
frasco_upload.egg-info/PKG-INFO
frasco_upload.egg-info/SOURCES.txt
frasco_upload.egg-info/dependency_links.txt
frasco_upload.egg-info/not-zip-safe
frasco_upload.egg-info/requires.txt
frasco_upload.egg-info/top_level.txt