Metadata-Version: 1.0
Name: frasco-upload
Version: 0.3.3
Summary: File uploading for Frasco
Home-page: http://github.com/frascoweb/frasco-upload
Author: Maxime Bouroumeau-Fuseau
Author-email: maxime.bouroumeau@gmail.com
License: MIT
Platform: any
